{
  "XYO": {
    "last_signal": "buy",
    "signal_count": 2,
    "monitoring_8h": true,
    "monitoring_direction": "buy",
    "last_2h_time": 1758877931.7391095,
    "last_8h_time": 0
  },
  "OKB": {
    "last_signal": "sell",
    "signal_count": 1,
    "monitoring_8h": false,
    "monitoring_direction": null,
    "last_2h_time": 1759558767.0860305,
    "last_8h_time": 0
  },
  "NEAR": {
    "last_signal": "sell",
    "signal_count": 1,
    "monitoring_8h": false,
    "monitoring_direction": null,
    "last_2h_time": 1759539763.779496,
    "last_8h_time": 0
  },
  "SUN": {
    "last_signal": "sell",
    "signal_count": 2,
    "monitoring_8h": true,
    "monitoring_direction": "sell",
    "last_2h_time": 1759885549.368957,
    "last_8h_time": 0
  },
  "FORM": {
    "last_signal": "sell",
    "signal_count": 1,
    "monitoring_8h": false,
    "monitoring_direction": null,
    "last_2h_time": 1759083484.193093,
    "last_8h_time": 0
  },
  "IP": {
    "last_signal": "buy",
    "signal_count": 1,
    "monitoring_8h": false,
    "monitoring_direction": null,
    "last_2h_time": 1759918546.0759223,
    "last_8h_time": 0
  },
  "SSV": {
    "last_signal": "buy",
    "signal_count": 1,
    "monitoring_8h": false,
    "monitoring_direction": null,
    "last_2h_time": 1758889779.9698474,
    "last_8h_time": 0
  },
  "CAKE": {
    "last_signal": "sell",
    "signal_count": 2,
    "monitoring_8h": true,
    "monitoring_direction": "sell",
    "last_2h_time": 1759885549.3649037,
    "last_8h_time": 0
  },
  "TOSHI": {
    "last_signal": "sell",
    "signal_count": 2,
    "monitoring_8h": true,
    "monitoring_direction": "sell",
    "last_2h_time": 1759978651.2612789,
    "last_8h_time": 0
  },
  "ZRO": {
    "last_signal": "sell",
    "signal_count": 1,
    "monitoring_8h": false,
    "monitoring_direction": null,
    "last_2h_time": 1759522548.6927872,
    "last_8h_time": 0
  },
  "TWT": {
    "last_signal": "sell",
    "signal_count": 2,
    "monitoring_8h": true,
    "monitoring_direction": "sell",
    "last_2h_time": 1759774938.2416592,
    "last_8h_time": 0
  },
  "TRX": {
    "last_signal": "buy",
    "signal_count": 1,
    "monitoring_8h": false,
    "monitoring_direction": null,
    "last_2h_time": 1759897057.9090552,
    "last_8h_time": 0
  },
  "MNT": {
    "last_signal": "sell",
    "signal_count": 2,
    "monitoring_8h": true,
    "monitoring_direction": "sell",
    "last_2h_time": 1759978651.2584898,
    "last_8h_time": 0
  },
  "GRASS": {
    "last_signal": "sell",
    "signal_count": 1,
    "monitoring_8h": false,
    "monitoring_direction": null,
    "last_2h_time": 1759453516.710081,
    "last_8h_time": 0
  },
  "KAITO": {
    "last_signal": "buy",
    "signal_count": 1,
    "monitoring_8h": false,
    "monitoring_direction": null,
    "last_2h_time": 1759868160.3726757,
    "last_8h_time": 0
  },
  "MYX": {
    "last_signal": "buy",
    "signal_count": 1,
    "monitoring_8h": false,
    "monitoring_direction": null,
    "last_2h_time": 1759443233.2224078,
    "last_8h_time": 0
  },
  "APT": {
    "last_signal": "sell",
    "signal_count": 2,
    "monitoring_8h": true,
    "monitoring_direction": "sell",
    "last_2h_time": 1759515626.054638,
    "last_8h_time": 0
  },
  "XPL": {
    "last_signal": "sell",
    "signal_count": 1,
    "monitoring_8h": false,
    "monitoring_direction": null,
    "last_2h_time": 1759810698.4122674,
    "last_8h_time": 0
  },
  "IMX": {
    "last_signal": "buy",
    "signal_count": 1,
    "monitoring_8h": false,
    "monitoring_direction": null,
    "last_2h_time": 1759911643.0607314,
    "last_8h_time": 0
  },
  "QNT": {
    "last_signal": "sell",
    "signal_count": 2,
    "monitoring_8h": true,
    "monitoring_direction": "sell",
    "last_2h_time": 1759400079.9484298,
    "last_8h_time": 0
  },
  "EIGEN": {
    "last_signal": "sell",
    "signal_count": 2,
    "monitoring_8h": true,
    "monitoring_direction": "sell",
    "last_2h_time": 1759645183.1188123,
    "last_8h_time": 0
  },
  "RENDER": {
    "last_signal": "buy",
    "signal_count": 2,
    "monitoring_8h": true,
    "monitoring_direction": "buy",
    "last_2h_time": 1759904560.6521068,
    "last_8h_time": 0
  },
  "RUNE": {
    "last_signal": "buy",
    "signal_count": 1,
    "monitoring_8h": false,
    "monitoring_direction": null,
    "last_2h_time": 1759868160.3688774,
    "last_8h_time": 0
  },
  "AVNT": {
    "last_signal": "buy",
    "signal_count": 2,
    "monitoring_8h": true,
    "monitoring_direction": "buy",
    "last_2h_time": 1759897057.9135654,
    "last_8h_time": 0
  },
  "GALA": {
    "last_signal": "buy",
    "signal_count": 2,
    "monitoring_8h": true,
    "monitoring_direction": "buy",
    "last_2h_time": 1759904560.6558707,
    "last_8h_time": 0
  },
  "TAO": {
    "last_signal": "sell",
    "signal_count": 2,
    "monitoring_8h": true,
    "monitoring_direction": "sell",
    "last_2h_time": 1759788816.0181081,
    "last_8h_time": 0
  },
  "WIF": {
    "last_signal": "sell",
    "signal_count": 1,
    "monitoring_8h": false,
    "monitoring_direction": null,
    "last_2h_time": 1759386116.025623,
    "last_8h_time": 0
  },
  "BTC": {
    "last_signal": "buy",
    "signal_count": 2,
    "monitoring_8h": true,
    "monitoring_direction": "buy",
    "last_2h_time": 1759885549.3526347,
    "last_8h_time": 0
  },
  "WLFI": {
    "last_signal": "buy",
    "signal_count": 1,
    "monitoring_8h": false,
    "monitoring_direction": null,
    "last_2h_time": 1759861302.5582225,
    "last_8h_time": 0
  },
  "AWE": {
    "last_signal": "buy",
    "signal_count": 1,
    "monitoring_8h": false,
    "monitoring_direction": null,
    "last_2h_time": 1759436154.3842015,
    "last_8h_time": 0
  },
  "XRP": {
    "last_signal": "buy",
    "signal_count": 1,
    "monitoring_8h": false,
    "monitoring_direction": null,
    "last_2h_time": 1759875253.9157584,
    "last_8h_time": 0
  },
  "ETH": {
    "last_signal": "sell",
    "signal_count": 2,
    "monitoring_8h": true,
    "monitoring_direction": "sell",
    "last_2h_time": 1759465051.5341625,
    "last_8h_time": 0
  },
  "POL": {
    "last_signal": "sell",
    "signal_count": 2,
    "monitoring_8h": true,
    "monitoring_direction": "sell",
    "last_2h_time": 1759788816.019666,
    "last_8h_time": 0
  },
  "CRV": {
    "last_signal": "buy",
    "signal_count": 1,
    "monitoring_8h": false,
    "monitoring_direction": null,
    "last_2h_time": 1759911643.0621016,
    "last_8h_time": 0
  },
  "AERO": {
    "last_signal": "buy",
    "signal_count": 2,
    "monitoring_8h": true,
    "monitoring_direction": "buy",
    "last_2h_time": 1759885549.3636363,
    "last_8h_time": 0
  },
  "MORPHO": {
    "last_signal": "buy",
    "signal_count": 2,
    "monitoring_8h": true,
    "monitoring_direction": "buy",
    "last_2h_time": 1759904560.6571364,
    "last_8h_time": 0
  },
  "BNB": {
    "last_signal": "sell",
    "signal_count": 2,
    "monitoring_8h": true,
    "monitoring_direction": "sell",
    "last_2h_time": 1759846568.3304255,
    "last_8h_time": 0
  },
  "ETHFI": {
    "last_signal": "buy",
    "signal_count": 1,
    "monitoring_8h": false,
    "monitoring_direction": null,
    "last_2h_time": 1759932947.4184425,
    "last_8h_time": 0
  },
  "AVAX": {
    "last_signal": "buy",
    "signal_count": 1,
    "monitoring_8h": false,
    "monitoring_direction": null,
    "last_2h_time": 1759875253.9132664,
    "last_8h_time": 0
  },
  "LINK": {
    "last_signal": "sell",
    "signal_count": 2,
    "monitoring_8h": true,
    "monitoring_direction": "sell",
    "last_2h_time": 1759805691.6242235,
    "last_8h_time": 0
  },
  "SOL": {
    "last_signal": "buy",
    "signal_count": 1,
    "monitoring_8h": false,
    "monitoring_direction": null,
    "last_2h_time": 1759875253.9106119,
    "last_8h_time": 0
  },
  "STRK": {
    "last_signal": "sell",
    "signal_count": 2,
    "monitoring_8h": true,
    "monitoring_direction": "sell",
    "last_2h_time": 1759781802.8584118,
    "last_8h_time": 0
  },
  "LDO": {
    "last_signal": "sell",
    "signal_count": 2,
    "monitoring_8h": true,
    "monitoring_direction": "sell",
    "last_2h_time": 1759453516.6985002,
    "last_8h_time": 0
  },
  "S": {
    "last_signal": "sell",
    "signal_count": 2,
    "monitoring_8h": true,
    "monitoring_direction": "sell",
    "last_2h_time": 1759846568.3318884,
    "last_8h_time": 0
  },
  "ENA": {
    "last_signal": "buy",
    "signal_count": 2,
    "monitoring_8h": true,
    "monitoring_direction": "buy",
    "last_2h_time": 1759904560.6459467,
    "last_8h_time": 0
  },
  "PLUME": {
    "last_signal": "sell",
    "signal_count": 2,
    "monitoring_8h": true,
    "monitoring_direction": "sell",
    "last_2h_time": 1759788816.0253775,
    "last_8h_time": 0
  },
  "TON": {
    "last_signal": "buy",
    "signal_count": 2,
    "monitoring_8h": true,
    "monitoring_direction": "buy",
    "last_2h_time": 1759904560.6446254,
    "last_8h_time": 0
  },
  "WLD": {
    "last_signal": "buy",
    "signal_count": 2,
    "monitoring_8h": true,
    "monitoring_direction": "buy",
    "last_2h_time": 1759601907.6812365,
    "last_8h_time": 0
  },
  "PENGU": {
    "last_signal": "sell",
    "signal_count": 2,
    "monitoring_8h": true,
    "monitoring_direction": "sell",
    "last_2h_time": 1759349836.8841674,
    "last_8h_time": 0
  },
  "JUP": {
    "last_signal": "buy",
    "signal_count": 1,
    "monitoring_8h": false,
    "monitoring_direction": null,
    "last_2h_time": 1759904560.6546135,
    "last_8h_time": 0
  },
  "ATH": {
    "last_signal": "sell",
    "signal_count": 1,
    "monitoring_8h": false,
    "monitoring_direction": null,
    "last_2h_time": 1759659236.0307739,
    "last_8h_time": 0
  },
  "W": {
    "last_signal": "sell",
    "signal_count": 2,
    "monitoring_8h": true,
    "monitoring_direction": "sell",
    "last_2h_time": 1759386116.0244548,
    "last_8h_time": 0
  },
  "AXS": {
    "last_signal": "sell",
    "signal_count": 2,
    "monitoring_8h": true,
    "monitoring_direction": "sell",
    "last_2h_time": 1759799170.1311512,
    "last_8h_time": 0
  },
  "MOVE": {
    "last_signal": "buy",
    "signal_count": 1,
    "monitoring_8h": false,
    "monitoring_direction": null,
    "last_2h_time": 1759892092.4071398,
    "last_8h_time": 0
  },
  "KSM": {
    "last_signal": "sell",
    "signal_count": 2,
    "monitoring_8h": true,
    "monitoring_direction": "sell",
    "last_2h_time": 1759810698.4137027,
    "last_8h_time": 0
  },
  "FET": {
    "last_signal": "buy",
    "signal_count": 2,
    "monitoring_8h": true,
    "monitoring_direction": "buy",
    "last_2h_time": 1759885549.3609939,
    "last_8h_time": 0
  },
  "KAIA": {
    "last_signal": "buy",
    "signal_count": 2,
    "monitoring_8h": true,
    "monitoring_direction": "buy",
    "last_2h_time": 1759875253.923229,
    "last_8h_time": 0
  },
  "PENDLE": {
    "last_signal": "sell",
    "signal_count": 1,
    "monitoring_8h": false,
    "monitoring_direction": null,
    "last_2h_time": 1759799170.129812,
    "last_8h_time": 0
  },
  "ZORA": {
    "last_signal": "sell",
    "signal_count": 2,
    "monitoring_8h": true,
    "monitoring_direction": "sell",
    "last_2h_time": 1759853918.6783526,
    "last_8h_time": 0
  },
  "PUMP": {
    "last_signal": "sell",
    "signal_count": 1,
    "monitoring_8h": false,
    "monitoring_direction": null,
    "last_2h_time": 1759321905.1799793,
    "last_8h_time": 0
  },
  "BCH": {
    "last_signal": "buy",
    "signal_count": 1,
    "monitoring_8h": false,
    "monitoring_direction": null,
    "last_2h_time": 1759868160.3637714,
    "last_8h_time": 0
  },
  "CHZ": {
    "last_signal": "buy",
    "signal_count": 1,
    "monitoring_8h": false,
    "monitoring_direction": null,
    "last_2h_time": 1759892092.4045262,
    "last_8h_time": 0
  },
  "SKY": {
    "last_signal": "sell",
    "signal_count": 1,
    "monitoring_8h": false,
    "monitoring_direction": null,
    "last_2h_time": 1759818144.8194234,
    "last_8h_time": 0
  },
  "APE": {
    "last_signal": "sell",
    "signal_count": 2,
    "monitoring_8h": true,
    "monitoring_direction": "sell",
    "last_2h_time": 1759373640.3887794,
    "last_8h_time": 0
  },
  "DOGE": {
    "last_signal": "sell",
    "signal_count": 2,
    "monitoring_8h": true,
    "monitoring_direction": "sell",
    "last_2h_time": 1759453516.6937828,
    "last_8h_time": 0
  },
  "ADA": {
    "last_signal": "buy",
    "signal_count": 1,
    "monitoring_8h": false,
    "monitoring_direction": null,
    "last_2h_time": 1759904560.643111,
    "last_8h_time": 0
  },
  "LTC": {
    "last_signal": "buy",
    "signal_count": 1,
    "monitoring_8h": false,
    "monitoring_direction": null,
    "last_2h_time": 1759868160.3663101,
    "last_8h_time": 0
  },
  "ONDO": {
    "last_signal": "buy",
    "signal_count": 2,
    "monitoring_8h": true,
    "monitoring_direction": "buy",
    "last_2h_time": 1759601907.6799183,
    "last_8h_time": 0
  },
  "ALGO": {
    "last_signal": "buy",
    "signal_count": 1,
    "monitoring_8h": false,
    "monitoring_direction": null,
    "last_2h_time": 1759608879.987468,
    "last_8h_time": 0
  },
  "INJ": {
    "last_signal": "buy",
    "signal_count": 2,
    "monitoring_8h": true,
    "monitoring_direction": "buy",
    "last_2h_time": 1759885549.3623633,
    "last_8h_time": 0
  },
  "GRT": {
    "last_signal": "buy",
    "signal_count": 1,
    "monitoring_8h": false,
    "monitoring_direction": null,
    "last_2h_time": 1759601907.6850436,
    "last_8h_time": 0
  },
  "RAY": {
    "last_signal": "buy",
    "signal_count": 1,
    "monitoring_8h": false,
    "monitoring_direction": null,
    "last_2h_time": 1759601907.687423,
    "last_8h_time": 0
  },
  "MANA": {
    "last_signal": "sell",
    "signal_count": 2,
    "monitoring_8h": true,
    "monitoring_direction": "sell",
    "last_2h_time": 1759472483.7249224,
    "last_8h_time": 0
  },
  "MEW": {
    "last_signal": "buy",
    "signal_count": 1,
    "monitoring_8h": false,
    "monitoring_direction": null,
    "last_2h_time": 1759885549.3715296,
    "last_8h_time": 0
  },
  "POPCAT": {
    "last_signal": "sell",
    "signal_count": 2,
    "monitoring_8h": true,
    "monitoring_direction": "sell",
    "last_2h_time": 1759349836.8877096,
    "last_8h_time": 0
  },
  "PNUT": {
    "last_signal": "sell",
    "signal_count": 2,
    "monitoring_8h": true,
    "monitoring_direction": "sell",
    "last_2h_time": 1759393182.7896917,
    "last_8h_time": 0
  },
  "VET": {
    "last_signal": "sell",
    "signal_count": 1,
    "monitoring_8h": false,
    "monitoring_direction": null,
    "last_2h_time": 1759349836.8832128,
    "last_8h_time": 0
  },
  "SEI": {
    "last_signal": "buy",
    "signal_count": 2,
    "monitoring_8h": true,
    "monitoring_direction": "buy",
    "last_2h_time": 1759911643.0594049,
    "last_8h_time": 0
  },
  "XLM": {
    "last_signal": "buy",
    "signal_count": 2,
    "monitoring_8h": true,
    "monitoring_direction": "buy",
    "last_2h_time": 1759911643.0579543,
    "last_8h_time": 0
  },
  "SUI": {
    "last_signal": "buy",
    "signal_count": 1,
    "monitoring_8h": false,
    "monitoring_direction": null,
    "last_2h_time": 1759885549.3540823,
    "last_8h_time": 0
  },
  "UNI": {
    "last_signal": "buy",
    "signal_count": 2,
    "monitoring_8h": true,
    "monitoring_direction": "buy",
    "last_2h_time": 1759875253.9169872,
    "last_8h_time": 0
  },
  "DOT": {
    "last_signal": "sell",
    "signal_count": 2,
    "monitoring_8h": true,
    "monitoring_direction": "sell",
    "last_2h_time": 1759414472.4333177,
    "last_8h_time": 0
  },
  "ETC": {
    "last_signal": "sell",
    "signal_count": 2,
    "monitoring_8h": true,
    "monitoring_direction": "sell",
    "last_2h_time": 1759378619.5444546,
    "last_8h_time": 0
  },
  "OP": {
    "last_signal": "sell",
    "signal_count": 2,
    "monitoring_8h": true,
    "monitoring_direction": "sell",
    "last_2h_time": 1759453516.6973484,
    "last_8h_time": 0
  },
  "STX": {
    "last_signal": "sell",
    "signal_count": 2,
    "monitoring_8h": true,
    "monitoring_direction": "sell",
    "last_2h_time": 1759818144.820954,
    "last_8h_time": 0
  },
  "SAND": {
    "last_signal": "buy",
    "signal_count": 1,
    "monitoring_8h": false,
    "monitoring_direction": null,
    "last_2h_time": 1759892092.4005682,
    "last_8h_time": 0
  },
  "DEEP": {
    "last_signal": "buy",
    "signal_count": 2,
    "monitoring_8h": true,
    "monitoring_direction": "buy",
    "last_2h_time": 1759892092.403208,
    "last_8h_time": 0
  },
  "ZRX": {
    "last_signal": "sell",
    "signal_count": 2,
    "monitoring_8h": true,
    "monitoring_direction": "sell",
    "last_2h_time": 1759453516.7112422,
    "last_8h_time": 0
  },
  "FIL": {
    "last_signal": "buy",
    "signal_count": 1,
    "monitoring_8h": false,
    "monitoring_direction": null,
    "last_2h_time": 1759904560.653356,
    "last_8h_time": 0
  },
  "KAS": {
    "last_signal": "buy",
    "signal_count": 2,
    "monitoring_8h": true,
    "monitoring_direction": "buy",
    "last_2h_time": 1759702385.7724767,
    "last_8h_time": 0
  },
  "ICP": {
    "last_signal": "sell",
    "signal_count": 1,
    "monitoring_8h": false,
    "monitoring_direction": null,
    "last_2h_time": 1759378619.5454578,
    "last_8h_time": 0
  },
  "SNX": {
    "last_signal": "sell",
    "signal_count": 1,
    "monitoring_8h": false,
    "monitoring_direction": null,
    "last_2h_time": 1759378619.5544653,
    "last_8h_time": 0
  },
  "SHIB": {
    "last_signal": "buy",
    "signal_count": 2,
    "monitoring_8h": true,
    "monitoring_direction": "buy",
    "last_2h_time": 1759904560.647322,
    "last_8h_time": 0
  },
  "PYTH": {
    "last_signal": "sell",
    "signal_count": 2,
    "monitoring_8h": true,
    "monitoring_direction": "sell",
    "last_2h_time": 1759781802.8571303,
    "last_8h_time": 0
  },
  "ENS": {
    "last_signal": "sell",
    "signal_count": 1,
    "monitoring_8h": false,
    "monitoring_direction": null,
    "last_2h_time": 1759386116.0176306,
    "last_8h_time": 0
  },
  "CFX": {
    "last_signal": "buy",
    "signal_count": 2,
    "monitoring_8h": true,
    "monitoring_direction": "buy",
    "last_2h_time": 1759885549.3662686,
    "last_8h_time": 0
  },
  "HYPE": {
    "last_signal": "buy",
    "signal_count": 2,
    "monitoring_8h": true,
    "monitoring_direction": "buy",
    "last_2h_time": 1759868160.3622537,
    "last_8h_time": 0
  },
  "A": {
    "last_signal": "buy",
    "signal_count": 1,
    "monitoring_8h": false,
    "monitoring_direction": null,
    "last_2h_time": 1759608880.0002148,
    "last_8h_time": 0
  },
  "JTO": {
    "last_signal": "buy",
    "signal_count": 2,
    "monitoring_8h": true,
    "monitoring_direction": "buy",
    "last_2h_time": 1759601907.6899421,
    "last_8h_time": 0
  },
  "BRETT": {
    "last_signal": "buy",
    "signal_count": 1,
    "monitoring_8h": false,
    "monitoring_direction": null,
    "last_2h_time": 1759904560.6584725,
    "last_8h_time": 0
  },
  "CRO": {
    "last_signal": "buy",
    "signal_count": 2,
    "monitoring_8h": true,
    "monitoring_direction": "buy",
    "last_2h_time": 1759875253.9144855,
    "last_8h_time": 0
  },
  "FARTCOIN": {
    "last_signal": "sell",
    "signal_count": 1,
    "monitoring_8h": false,
    "monitoring_direction": null,
    "last_2h_time": 1759805691.6256633,
    "last_8h_time": 0
  },
  "ARB": {
    "last_signal": "sell",
    "signal_count": 1,
    "monitoring_8h": false,
    "monitoring_direction": null,
    "last_2h_time": 1759453516.6961534,
    "last_8h_time": 0
  },
  "VIRTUAL": {
    "last_signal": "buy",
    "signal_count": 1,
    "monitoring_8h": false,
    "monitoring_direction": null,
    "last_2h_time": 1759608879.9972746,
    "last_8h_time": 0
  },
  "STBL": {
    "last_signal": "buy",
    "signal_count": 2,
    "monitoring_8h": true,
    "monitoring_direction": "buy",
    "last_2h_time": 1759545939.7511477,
    "last_8h_time": 0
  },
  "PI": {
    "last_signal": "buy",
    "signal_count": 2,
    "monitoring_8h": true,
    "monitoring_direction": "buy",
    "last_2h_time": 1759904560.6508195,
    "last_8h_time": 0
  },
  "0G": {
    "last_signal": "buy",
    "signal_count": 1,
    "monitoring_8h": false,
    "monitoring_direction": null,
    "last_2h_time": 1759897057.9118102,
    "last_8h_time": 0
  },
  "THETA": {
    "last_signal": "sell",
    "signal_count": 2,
    "monitoring_8h": true,
    "monitoring_direction": "sell",
    "last_2h_time": 1759788816.0239604,
    "last_8h_time": 0
  },
  "ASTER": {
    "last_signal": "sell",
    "signal_count": 1,
    "monitoring_8h": false,
    "monitoring_direction": null,
    "last_2h_time": 1759545939.7485473,
    "last_8h_time": 0
  },
  "FLOKI": {
    "last_signal": "sell",
    "signal_count": 1,
    "monitoring_8h": false,
    "monitoring_direction": null,
    "last_2h_time": 1759565835.4751399,
    "last_8h_time": 0
  },
  "LINEA": {
    "last_signal": "buy",
    "signal_count": 1,
    "monitoring_8h": false,
    "monitoring_direction": null,
    "last_2h_time": 1759702385.773898,
    "last_8h_time": 0
  },
  "HBAR": {
    "last_signal": "sell",
    "signal_count": 1,
    "monitoring_8h": false,
    "monitoring_direction": null,
    "last_2h_time": 1759799170.1283784,
    "last_8h_time": 0
  },
  "MERL": {
    "last_signal": "buy",
    "signal_count": 1,
    "monitoring_8h": false,
    "monitoring_direction": null,
    "last_2h_time": 1759978651.259905,
    "last_8h_time": 0
  },
  "BIO": {
    "last_signal": "buy",
    "signal_count": 2,
    "monitoring_8h": true,
    "monitoring_direction": "buy",
    "last_2h_time": 1759868160.3739913,
    "last_8h_time": 0
  },
  "BARD": {
    "last_signal": "buy",
    "signal_count": 2,
    "monitoring_8h": true,
    "monitoring_direction": "buy",
    "last_2h_time": 1759892092.4084587,
    "last_8h_time": 0
  },
  "BERA": {
    "last_signal": "buy",
    "signal_count": 2,
    "monitoring_8h": true,
    "monitoring_direction": "buy",
    "last_2h_time": 1759892092.4058282,
    "last_8h_time": 0
  },
  "AAVE": {
    "last_signal": "buy",
    "signal_count": 1,
    "monitoring_8h": false,
    "monitoring_direction": null,
    "last_2h_time": 1759885549.3583882,
    "last_8h_time": 0
  },
  "AR": {
    "last_signal": "buy",
    "signal_count": 2,
    "monitoring_8h": true,
    "monitoring_direction": "buy",
    "last_2h_time": 1759904560.659729,
    "last_8h_time": 0
  }
}