{
  "updated_at": "2025-09-23T10:18:01.410973",
  "source": "CoinMarketCap-Unlimited",
  "dataset_type": "CipherB-BBW",
  "filters_applied": {
    "min_market_cap": 100000000,
    "min_volume_24h": 10000000,
    "expected_coins": 1000
  },
  "total_coins": 232,
  "coins": [
    {
      "id": 1,
      "symbol": "BTC",
      "name": "Bitcoin",
      "current_price": 113005.30826923662,
      "market_cap": 2251632462344.1636,
      "total_volume": 53204458987.62356,
      "price_change_percentage_24h": 0.37187413,
      "market_cap_rank": 1
    },
    {
      "id": 1027,
      "symbol": "ETH",
      "name": "Ethereum",
      "current_price": 4195.523354790124,
      "market_cap": 506415404124.08606,
      "total_volume": 35883528082.60232,
      "price_change_percentage_24h": 0.70458673,
      "market_cap_rank": 2
    },
    {
      "id": 52,
      "symbol": "XRP",
      "name": "XRP",
      "current_price": 2.8638822833684796,
      "market_cap": 171194982820.3475,
      "total_volume": 6910294317.690685,
      "price_change_percentage_24h": 1.82959758,
      "market_cap_rank": 4
    },
    {
      "id": 1839,
      "symbol": "BNB",
      "name": "BNB",
      "current_price": 999.687958582,
      "market_cap": 139142811577.22775,
      "total_volume": 4281762527.204512,
      "price_change_percentage_24h": -2.00972407,
      "market_cap_rank": 5
    },
    {
      "id": 5426,
      "symbol": "SOL",
      "name": "Solana",
      "current_price": 218.74539649044698,
      "market_cap": 118839383123.55959,
      "total_volume": 8813534513.626657,
      "price_change_percentage_24h": -1.23787467,
      "market_cap_rank": 6
    },
    {
      "id": 74,
      "symbol": "DOGE",
      "name": "Dogecoin",
      "current_price": 0.24095368085724161,
      "market_cap": 36398218795.71772,
      "total_volume": 3294335982.9039507,
      "price_change_percentage_24h": 0.88249995,
      "market_cap_rank": 8
    },
    {
      "id": 1958,
      "symbol": "TRX",
      "name": "TRON",
      "current_price": 0.3399104628058481,
      "market_cap": 32178121470.375526,
      "total_volume": 827319324.8229104,
      "price_change_percentage_24h": 1.28786825,
      "market_cap_rank": 9
    },
    {
      "id": 2010,
      "symbol": "ADA",
      "name": "Cardano",
      "current_price": 0.8241717815607932,
      "market_cap": 29505723533.857143,
      "total_volume": 1350897844.9089599,
      "price_change_percentage_24h": 0.6256939,
      "market_cap_rank": 10
    },
    {
      "id": 32196,
      "symbol": "HYPE",
      "name": "Hyperliquid",
      "current_price": 48.17420128458647,
      "market_cap": 16086723357.915623,
      "total_volume": 474870374.5020075,
      "price_change_percentage_24h": -1.82753916,
      "market_cap_rank": 11
    },
    {
      "id": 1975,
      "symbol": "LINK",
      "name": "Chainlink",
      "current_price": 21.81654958716856,
      "market_cap": 14793801630.440756,
      "total_volume": 873918578.8585353,
      "price_change_percentage_24h": 2.79353625,
      "market_cap_rank": 12
    },
    {
      "id": 5805,
      "symbol": "AVAX",
      "name": "Avalanche",
      "current_price": 34.790407492624894,
      "market_cap": 14691129256.232418,
      "total_volume": 2677527314.153371,
      "price_change_percentage_24h": 12.41038264,
      "market_cap_rank": 13
    },
    {
      "id": 20947,
      "symbol": "SUI",
      "name": "Sui",
      "current_price": 3.3723700832834513,
      "market_cap": 12035428023.416529,
      "total_volume": 1105908661.463629,
      "price_change_percentage_24h": 0.56066194,
      "market_cap_rank": 15
    },
    {
      "id": 512,
      "symbol": "XLM",
      "name": "Stellar",
      "current_price": 0.3718552487480294,
      "market_cap": 11856145895.40971,
      "total_volume": 279689672.84728485,
      "price_change_percentage_24h": 4.0616641,
      "market_cap_rank": 16
    },
    {
      "id": 1831,
      "symbol": "BCH",
      "name": "Bitcoin Cash",
      "current_price": 562.4407097302931,
      "market_cap": 11209086546.599506,
      "total_volume": 462917146.2245184,
      "price_change_percentage_24h": -1.57726364,
      "market_cap_rank": 17
    },
    {
      "id": 4642,
      "symbol": "HBAR",
      "name": "Hedera",
      "current_price": 0.22330996130993228,
      "market_cap": 9466762785.543934,
      "total_volume": 287814056.2703267,
      "price_change_percentage_24h": 3.43757787,
      "market_cap_rank": 18
    },
    {
      "id": 2,
      "symbol": "LTC",
      "name": "Litecoin",
      "current_price": 106.13573954232999,
      "market_cap": 8101337229.693013,
      "total_volume": 557540434.1489265,
      "price_change_percentage_24h": 0.35283972,
      "market_cap_rank": 20
    },
    {
      "id": 3635,
      "symbol": "CRO",
      "name": "Cronos",
      "current_price": 0.21345529551521283,
      "market_cap": 7433074495.397043,
      "total_volume": 91721082.46757858,
      "price_change_percentage_24h": 7.18854082,
      "market_cap_rank": 21
    },
    {
      "id": 5994,
      "symbol": "SHIB",
      "name": "Shiba Inu",
      "current_price": 1.2239853276557646e-05,
      "market_cap": 7212283185.123605,
      "total_volume": 260649860.66195932,
      "price_change_percentage_24h": 1.27077149,
      "market_cap_rank": 22
    },
    {
      "id": 11419,
      "symbol": "TON",
      "name": "Toncoin",
      "current_price": 2.82127879496785,
      "market_cap": 7179978812.326464,
      "total_volume": 170189577.09139362,
      "price_change_percentage_24h": -0.14387412,
      "market_cap_rank": 23
    },
    {
      "id": 6636,
      "symbol": "DOT",
      "name": "Polkadot",
      "current_price": 4.017225940943077,
      "market_cap": 6507811458.512673,
      "total_volume": 294881412.091735,
      "price_change_percentage_24h": 0.99947167,
      "market_cap_rank": 24
    },
    {
      "id": 27075,
      "symbol": "MNT",
      "name": "Mantle",
      "current_price": 1.7798177187296425,
      "market_cap": 5789647468.436695,
      "total_volume": 585492727.0467547,
      "price_change_percentage_24h": 9.73582406,
      "market_cap_rank": 25
    },
    {
      "id": 328,
      "symbol": "XMR",
      "name": "Monero",
      "current_price": 292.45403654190665,
      "market_cap": 5394824765.411853,
      "total_volume": 101217163.48359443,
      "price_change_percentage_24h": 0.06038692,
      "market_cap_rank": 26
    },
    {
      "id": 7083,
      "symbol": "UNI",
      "name": "Uniswap",
      "current_price": 8.155793327686027,
      "market_cap": 5140845512.13403,
      "total_volume": 257623452.99277374,
      "price_change_percentage_24h": 0.42156411,
      "market_cap_rank": 28
    },
    {
      "id": 33251,
      "symbol": "WLFI",
      "name": "World Liberty Financial",
      "current_price": 0.20370588749489502,
      "market_cap": 5011235808.394562,
      "total_volume": 751809179.4486444,
      "price_change_percentage_24h": -3.5192386,
      "market_cap_rank": 29
    },
    {
      "id": 30171,
      "symbol": "ENA",
      "name": "Ethena",
      "current_price": 0.6141518927546492,
      "market_cap": 4230930773.6800756,
      "total_volume": 499064022.310128,
      "price_change_percentage_24h": 2.55984138,
      "market_cap_rank": 30
    },
    {
      "id": 7278,
      "symbol": "AAVE",
      "name": "Aave",
      "current_price": 270.9169821845651,
      "market_cap": 4126750040.6425333,
      "total_volume": 423921261.29668295,
      "price_change_percentage_24h": 2.06991687,
      "market_cap_rank": 31
    },
    {
      "id": 24478,
      "symbol": "PEPE",
      "name": "Pepe",
      "current_price": 9.735883096156921e-06,
      "market_cap": 4095787682.760886,
      "total_volume": 608842057.6067289,
      "price_change_percentage_24h": -0.35044809,
      "market_cap_rank": 32
    },
    {
      "id": 35626,
      "symbol": "IP",
      "name": "Story",
      "current_price": 12.95369981964081,
      "market_cap": 4052153928.818251,
      "total_volume": 394605618.60309905,
      "price_change_percentage_24h": -5.64689786,
      "market_cap_rank": 33
    },
    {
      "id": 3897,
      "symbol": "OKB",
      "name": "OKB",
      "current_price": 182.5913876390519,
      "market_cap": 3834419140.4200897,
      "total_volume": 129759385.28157876,
      "price_change_percentage_24h": -1.19090645,
      "market_cap_rank": 34
    },
    {
      "id": 6535,
      "symbol": "NEAR",
      "name": "NEAR Protocol",
      "current_price": 3.030427256355017,
      "market_cap": 3787540086.5575676,
      "total_volume": 400996206.72913164,
      "price_change_percentage_24h": 6.13233645,
      "market_cap_rank": 35
    },
    {
      "id": 22974,
      "symbol": "TAO",
      "name": "Bittensor",
      "current_price": 317.1466870451217,
      "market_cap": 3151116057.496877,
      "total_volume": 107254451.72897266,
      "price_change_percentage_24h": 2.92826779,
      "market_cap_rank": 37
    },
    {
      "id": 21794,
      "symbol": "APT",
      "name": "Aptos",
      "current_price": 4.347059811221107,
      "market_cap": 3052283727.5148883,
      "total_volume": 279208192.15541285,
      "price_change_percentage_24h": 1.72391566,
      "market_cap_rank": 38
    },
    {
      "id": 21159,
      "symbol": "ONDO",
      "name": "Ondo",
      "current_price": 0.9369846738205065,
      "market_cap": 2960035337.6239715,
      "total_volume": 170324411.03266776,
      "price_change_percentage_24h": 1.35662042,
      "market_cap_rank": 39
    },
    {
      "id": 1321,
      "symbol": "ETC",
      "name": "Ethereum Classic",
      "current_price": 18.845588593343706,
      "market_cap": 2895273673.170314,
      "total_volume": 137323318.8476404,
      "price_change_percentage_24h": 1.53132296,
      "market_cap_rank": 40
    },
    {
      "id": 36341,
      "symbol": "ASTER",
      "name": "Aster",
      "current_price": 1.6707130399066614,
      "market_cap": 2769541006.2532725,
      "total_volume": 2111806441.3499076,
      "price_change_percentage_24h": 10.54736084,
      "market_cap_rank": 41
    },
    {
      "id": 13502,
      "symbol": "WLD",
      "name": "Worldcoin",
      "current_price": 1.3212705507381912,
      "market_cap": 2706304112.2522526,
      "total_volume": 460612909.162773,
      "price_change_percentage_24h": -0.25651046,
      "market_cap_rank": 42
    },
    {
      "id": 35491,
      "symbol": "M",
      "name": "MemeCore",
      "current_price": 2.460362437475773,
      "market_cap": 2557549376.5024242,
      "total_volume": 34996686.31367011,
      "price_change_percentage_24h": -4.92379985,
      "market_cap_rank": 44
    },
    {
      "id": 28321,
      "symbol": "POL",
      "name": "POL (prev. MATIC)",
      "current_price": 0.22835347311711976,
      "market_cap": 2396850753.9152675,
      "total_volume": 155416526.56936422,
      "price_change_percentage_24h": 0.04053614,
      "market_cap_rank": 45
    },
    {
      "id": 11841,
      "symbol": "ARB",
      "name": "Arbitrum",
      "current_price": 0.4334728130541785,
      "market_cap": 2342326960.7888937,
      "total_volume": 369519854.0928864,
      "price_change_percentage_24h": -0.86984461,
      "market_cap_rank": 46
    },
    {
      "id": 8916,
      "symbol": "ICP",
      "name": "Internet Computer",
      "current_price": 4.32723019587908,
      "market_cap": 2328569313.459432,
      "total_volume": 94132236.7652315,
      "price_change_percentage_24h": -0.24696892,
      "market_cap_rank": 47
    },
    {
      "id": 35697,
      "symbol": "PI",
      "name": "Pi",
      "current_price": 0.2748823490939708,
      "market_cap": 2253087772.01765,
      "total_volume": 95494843.39408273,
      "price_change_percentage_24h": -3.95734056,
      "market_cap_rank": 48
    },
    {
      "id": 20396,
      "symbol": "KAS",
      "name": "Kaspa",
      "current_price": 0.07881816639729673,
      "market_cap": 2106819252.8960423,
      "total_volume": 52194083.33557296,
      "price_change_percentage_24h": 1.45928799,
      "market_cap_rank": 49
    },
    {
      "id": 36507,
      "symbol": "PUMP",
      "name": "Pump.fun",
      "current_price": 0.005729628004178484,
      "market_cap": 2028288313.4791832,
      "total_volume": 591154846.7018836,
      "price_change_percentage_24h": -3.8918992,
      "market_cap_rank": 50
    },
    {
      "id": 3077,
      "symbol": "VET",
      "name": "VeChain",
      "current_price": 0.022936886866456598,
      "market_cap": 1972229161.684461,
      "total_volume": 50465157.25066748,
      "price_change_percentage_24h": -0.2931637,
      "market_cap_rank": 51
    },
    {
      "id": 3794,
      "symbol": "ATOM",
      "name": "Cosmos",
      "current_price": 4.186325431337949,
      "market_cap": 1966232909.958265,
      "total_volume": 98025816.86588445,
      "price_change_percentage_24h": 0.71494512,
      "market_cap_rank": 52
    },
    {
      "id": 4030,
      "symbol": "ALGO",
      "name": "Algorand",
      "current_price": 0.215836351479155,
      "market_cap": 1895400989.9786773,
      "total_volume": 93596383.7413113,
      "price_change_percentage_24h": 1.68221668,
      "market_cap_rank": 54
    },
    {
      "id": 34466,
      "symbol": "PENGU",
      "name": "Pudgy Penguins",
      "current_price": 0.03003914843374177,
      "market_cap": 1888272768.7525125,
      "total_volume": 347239541.1274074,
      "price_change_percentage_24h": -1.31510029,
      "market_cap_rank": 55
    },
    {
      "id": 5690,
      "symbol": "RENDER",
      "name": "Render",
      "current_price": 3.639895628152917,
      "market_cap": 1887593877.202972,
      "total_volume": 73469910.96104717,
      "price_change_percentage_24h": -0.93004955,
      "market_cap_rank": 56
    },
    {
      "id": 36410,
      "symbol": "MYX",
      "name": "MYX Finance",
      "current_price": 9.604698530575329,
      "market_cap": 1893198268.0575836,
      "total_volume": 140263896.5595399,
      "price_change_percentage_24h": -1.5186386,
      "market_cap_rank": 57
    },
    {
      "id": 23149,
      "symbol": "SEI",
      "name": "Sei",
      "current_price": 0.294921068223455,
      "market_cap": 1807210767.8287883,
      "total_volume": 148722992.88212922,
      "price_change_percentage_24h": 1.07482216,
      "market_cap_rank": 58
    },
    {
      "id": 23095,
      "symbol": "BONK",
      "name": "Bonk",
      "current_price": 2.0862065322118917e-05,
      "market_cap": 1694848744.3529372,
      "total_volume": 293320000.94797194,
      "price_change_percentage_24h": 1.73420279,
      "market_cap_rank": 60
    },
    {
      "id": 2280,
      "symbol": "FIL",
      "name": "Filecoin",
      "current_price": 2.268167634898224,
      "market_cap": 1565706045.4377773,
      "total_volume": 131083557.4185623,
      "price_change_percentage_24h": 0.48958217,
      "market_cap_rank": 61
    },
    {
      "id": 33038,
      "symbol": "SKY",
      "name": "Sky",
      "current_price": 0.06597317006729074,
      "market_cap": 1545213093.8639746,
      "total_volume": 39367578.1892691,
      "price_change_percentage_24h": 1.48227801,
      "market_cap_rank": 62
    },
    {
      "id": 35336,
      "symbol": "TRUMP",
      "name": "OFFICIAL TRUMP",
      "current_price": 7.708210024072897,
      "market_cap": 1541636335.5525599,
      "total_volume": 271286322.9347139,
      "price_change_percentage_24h": 0.32460773,
      "market_cap_rank": 63
    },
    {
      "id": 29210,
      "symbol": "JUP",
      "name": "Jupiter",
      "current_price": 0.4747401061284429,
      "market_cap": 1477269887.7885435,
      "total_volume": 46529280.4536274,
      "price_change_percentage_24h": 0.54779893,
      "market_cap_rank": 64
    },
    {
      "id": 3773,
      "symbol": "FET",
      "name": "Artificial Superintelligence Alliance",
      "current_price": 0.5994590726910479,
      "market_cap": 1422291390.6309571,
      "total_volume": 65898884.11406124,
      "price_change_percentage_24h": 2.31781071,
      "market_cap_rank": 65
    },
    {
      "id": 27772,
      "symbol": "PYUSD",
      "name": "PayPal USD",
      "current_price": 0.99944164229149,
      "market_cap": 1401486954.329919,
      "total_volume": 105423397.5434128,
      "price_change_percentage_24h": -0.02530138,
      "market_cap_rank": 66
    },
    {
      "id": 2634,
      "symbol": "XDC",
      "name": "XDC Network",
      "current_price": 0.07815632447175791,
      "market_cap": 1386953581.827826,
      "total_volume": 45161855.11058713,
      "price_change_percentage_24h": 1.20773446,
      "market_cap_rank": 67
    },
    {
      "id": 4269,
      "symbol": "GT",
      "name": "GateToken",
      "current_price": 16.505273123846912,
      "market_cap": 1359504100.3231215,
      "total_volume": 21815167.07578935,
      "price_change_percentage_24h": 0.17146569,
      "market_cap_rank": 68
    },
    {
      "id": 10603,
      "symbol": "IMX",
      "name": "Immutable",
      "current_price": 0.6785436497518123,
      "market_cap": 1316332672.1456656,
      "total_volume": 65361151.78977118,
      "price_change_percentage_24h": -4.60680436,
      "market_cap_rank": 69
    },
    {
      "id": 38337,
      "symbol": "0G",
      "name": "0G",
      "current_price": 5.87772952151383,
      "market_cap": 1253390542.3302362,
      "total_volume": 3356151659.9134984,
      "price_change_percentage_24h": 48.350762,
      "market_cap_rank": 70
    },
    {
      "id": 11840,
      "symbol": "OP",
      "name": "Optimism",
      "current_price": 0.7013405886159108,
      "market_cap": 1247428490.0151014,
      "total_volume": 183997024.473922,
      "price_change_percentage_24h": -0.7737206,
      "market_cap_rank": 71
    },
    {
      "id": 7226,
      "symbol": "INJ",
      "name": "Injective",
      "current_price": 12.43314425914575,
      "market_cap": 1242953061.674272,
      "total_volume": 93634681.59099475,
      "price_change_percentage_24h": 0.74067459,
      "market_cap_rank": 72
    },
    {
      "id": 22861,
      "symbol": "TIA",
      "name": "Celestia",
      "current_price": 1.4971986017410506,
      "market_cap": 1184129652.7870603,
      "total_volume": 98867267.91091804,
      "price_change_percentage_24h": -0.77821223,
      "market_cap_rank": 73
    },
    {
      "id": 3155,
      "symbol": "QNT",
      "name": "Quant",
      "current_price": 92.46960461550105,
      "market_cap": 1116361309.486535,
      "total_volume": 23888993.78796508,
      "price_change_percentage_24h": 2.72467712,
      "market_cap_rank": 75
    },
    {
      "id": 4847,
      "symbol": "STX",
      "name": "Stacks",
      "current_price": 0.6048253031255063,
      "market_cap": 1088852395.7195158,
      "total_volume": 32087104.02840271,
      "price_change_percentage_24h": 0.59211922,
      "market_cap_rank": 77
    },
    {
      "id": 8000,
      "symbol": "LDO",
      "name": "Lido DAO",
      "current_price": 1.1271419135468315,
      "market_cap": 1009695471.0458,
      "total_volume": 101109234.51765886,
      "price_change_percentage_24h": 1.0834068,
      "market_cap_rank": 78
    },
    {
      "id": 29270,
      "symbol": "AERO",
      "name": "Aerodrome Finance",
      "current_price": 1.1254057824853458,
      "market_cap": 1008093224.6472862,
      "total_volume": 85114280.0758326,
      "price_change_percentage_24h": 4.80073631,
      "market_cap_rank": 79
    },
    {
      "id": 28081,
      "symbol": "SPX",
      "name": "SPX6900",
      "current_price": 1.0694596699472616,
      "market_cap": 995659562.8294435,
      "total_volume": 31422155.2825936,
      "price_change_percentage_24h": -1.71140573,
      "market_cap_rank": 80
    },
    {
      "id": 6538,
      "symbol": "CRV",
      "name": "Curve DAO Token",
      "current_price": 0.6879742834596008,
      "market_cap": 958044975.5932319,
      "total_volume": 159904421.99871957,
      "price_change_percentage_24h": -0.55146662,
      "market_cap_rank": 81
    },
    {
      "id": 32880,
      "symbol": "KAIA",
      "name": "Kaia",
      "current_price": 0.1515593068544598,
      "market_cap": 928437103.2902699,
      "total_volume": 35683752.5183205,
      "price_change_percentage_24h": 0.95129188,
      "market_cap_rank": 83
    },
    {
      "id": 7186,
      "symbol": "CAKE",
      "name": "PancakeSwap",
      "current_price": 2.6905111190207176,
      "market_cap": 928390240.6092081,
      "total_volume": 124161879.00700845,
      "price_change_percentage_24h": -1.06545085,
      "market_cap_rank": 84
    },
    {
      "id": 6719,
      "symbol": "GRT",
      "name": "The Graph",
      "current_price": 0.08461893725221896,
      "market_cap": 889358066.0639733,
      "total_volume": 49958238.90453675,
      "price_change_percentage_24h": 0.23082294,
      "market_cap_rank": 85
    },
    {
      "id": 28177,
      "symbol": "PYTH",
      "name": "Pyth Network",
      "current_price": 0.15271639725891406,
      "market_cap": 878116750.9320037,
      "total_volume": 61109980.27195796,
      "price_change_percentage_24h": 2.4902433,
      "market_cap_rank": 86
    },
    {
      "id": 7326,
      "symbol": "DEXE",
      "name": "DeXe",
      "current_price": 10.39847395426448,
      "market_cap": 870702152.1577514,
      "total_volume": 38856683.46431004,
      "price_change_percentage_24h": -4.92245044,
      "market_cap_rank": 87
    },
    {
      "id": 9481,
      "symbol": "PENDLE",
      "name": "Pendle",
      "current_price": 4.892761635030548,
      "market_cap": 827712098.2604704,
      "total_volume": 104418451.88533758,
      "price_change_percentage_24h": 5.03997323,
      "market_cap_rank": 88
    },
    {
      "id": 10804,
      "symbol": "FLOKI",
      "name": "FLOKI",
      "current_price": 8.647991834066586e-05,
      "market_cap": 824935842.7708973,
      "total_volume": 85142507.99304652,
      "price_change_percentage_24h": 0.58915786,
      "market_cap_rank": 89
    },
    {
      "id": 1437,
      "symbol": "ZEC",
      "name": "Zcash",
      "current_price": 49.09172203877877,
      "market_cap": 796695199.6290584,
      "total_volume": 98600929.7470641,
      "price_change_percentage_24h": 1.98979025,
      "market_cap_rank": 91
    },
    {
      "id": 28752,
      "symbol": "WIF",
      "name": "dogwifhat",
      "current_price": 0.7970413722691858,
      "market_cap": 796116771.527428,
      "total_volume": 240186656.76856712,
      "price_change_percentage_24h": 0.21576542,
      "market_cap_rank": 92
    },
    {
      "id": 13855,
      "symbol": "ENS",
      "name": "Ethereum Name Service",
      "current_price": 21.084950948368967,
      "market_cap": 780133632.5963354,
      "total_volume": 81211193.26853669,
      "price_change_percentage_24h": 1.53604138,
      "market_cap_rank": 93
    },
    {
      "id": 29814,
      "symbol": "ETHFI",
      "name": "ether.fi",
      "current_price": 1.4927827598446946,
      "market_cap": 765100780.0409949,
      "total_volume": 161233429.9771779,
      "price_change_percentage_24h": 11.79664231,
      "market_cap_rank": 94
    },
    {
      "id": 7334,
      "symbol": "CFX",
      "name": "Conflux",
      "current_price": 0.14720809816342592,
      "market_cap": 756373801.7842976,
      "total_volume": 98374856.1525132,
      "price_change_percentage_24h": -0.760037,
      "market_cap_rank": 95
    },
    {
      "id": 8526,
      "symbol": "RAY",
      "name": "Raydium",
      "current_price": 2.8073690594446927,
      "market_cap": 752731696.059519,
      "total_volume": 57230200.51774336,
      "price_change_percentage_24h": 2.72967482,
      "market_cap_rank": 96
    },
    {
      "id": 2416,
      "symbol": "THETA",
      "name": "Theta Network",
      "current_price": 0.7508915382581894,
      "market_cap": 750891538.2581894,
      "total_volume": 23370907.25587045,
      "price_change_percentage_24h": 1.31571583,
      "market_cap_rank": 97
    },
    {
      "id": 2011,
      "symbol": "XTZ",
      "name": "Tezos",
      "current_price": 0.7009308584461318,
      "market_cap": 742578638.3635697,
      "total_volume": 23051657.01806152,
      "price_change_percentage_24h": 0.28830624,
      "market_cap_rank": 98
    },
    {
      "id": 30083,
      "symbol": "ATH",
      "name": "Aethir",
      "current_price": 0.060453136855239856,
      "market_cap": 738142497.3229114,
      "total_volume": 97548359.54633309,
      "price_change_percentage_24h": 2.77197213,
      "market_cap_rank": 100
    },
    {
      "id": 32684,
      "symbol": "S",
      "name": "Sonic",
      "current_price": 0.2535404624136311,
      "market_cap": 730196531.7512575,
      "total_volume": 96370361.03304255,
      "price_change_percentage_24h": 2.32184456,
      "market_cap_rank": 101
    },
    {
      "id": 29420,
      "symbol": "VIRTUAL",
      "name": "Virtuals Protocol",
      "current_price": 1.1073748324430868,
      "market_cap": 726000842.3603926,
      "total_volume": 89942980.80083504,
      "price_change_percentage_24h": 1.07073177,
      "market_cap_rank": 102
    },
    {
      "id": 7080,
      "symbol": "GALA",
      "name": "Gala",
      "current_price": 0.015419919140653214,
      "market_cap": 710174383.3501577,
      "total_volume": 92656813.32456167,
      "price_change_percentage_24h": 0.05276063,
      "market_cap_rank": 103
    },
    {
      "id": 6210,
      "symbol": "SAND",
      "name": "The Sandbox",
      "current_price": 0.275493520543187,
      "market_cap": 708924498.9413369,
      "total_volume": 68520621.87046178,
      "price_change_percentage_24h": 2.03911423,
      "market_cap_rank": 104
    },
    {
      "id": 1720,
      "symbol": "IOTA",
      "name": "IOTA",
      "current_price": 0.17146867529357204,
      "market_cap": 693716246.2758402,
      "total_volume": 25005385.39843103,
      "price_change_percentage_24h": -0.5447439,
      "market_cap_rank": 105
    },
    {
      "id": 36462,
      "symbol": "A",
      "name": "Vaulta",
      "current_price": 0.4286124138283787,
      "market_cap": 682614421.7071407,
      "total_volume": 39034809.90456133,
      "price_change_percentage_24h": -0.547931,
      "market_cap_rank": 106
    },
    {
      "id": 3871,
      "symbol": "AB",
      "name": "AB",
      "current_price": 0.008370871522226481,
      "market_cap": 658571314.9776224,
      "total_volume": 31392398.96420959,
      "price_change_percentage_24h": -0.71494567,
      "market_cap_rank": 107
    },
    {
      "id": 8425,
      "symbol": "JASMY",
      "name": "JasmyCoin",
      "current_price": 0.01279015017630392,
      "market_cap": 632408971.3382977,
      "total_volume": 39173266.56133871,
      "price_change_percentage_24h": 1.02100734,
      "market_cap_rank": 108
    },
    {
      "id": 28541,
      "symbol": "JTO",
      "name": "Jito",
      "current_price": 1.6548343409268942,
      "market_cap": 629752470.6474502,
      "total_volume": 36135004.77787937,
      "price_change_percentage_24h": 0.44327809,
      "market_cap_rank": 109
    },
    {
      "id": 33597,
      "symbol": "FARTCOIN",
      "name": "Fartcoin",
      "current_price": 0.624114365725338,
      "market_cap": 624113277.2698841,
      "total_volume": 156322755.04082233,
      "price_change_percentage_24h": 0.51350611,
      "market_cap_rank": 110
    },
    {
      "id": 34104,
      "symbol": "MORPHO",
      "name": "Morpho",
      "current_price": 1.8058642122885342,
      "market_cap": 611828702.4803698,
      "total_volume": 28215042.40731072,
      "price_change_percentage_24h": -1.40920582,
      "market_cap_rank": 111
    },
    {
      "id": 10529,
      "symbol": "SUN",
      "name": "Sun [New]",
      "current_price": 0.03144835573581076,
      "market_cap": 602774463.0746619,
      "total_volume": 746813975.9203174,
      "price_change_percentage_24h": -1.25441156,
      "market_cap_rank": 112
    },
    {
      "id": 16086,
      "symbol": "BTT",
      "name": "BitTorrent [New]",
      "current_price": 6.066003582353752e-07,
      "market_cap": 598145042.4990396,
      "total_volume": 18752767.98410812,
      "price_change_percentage_24h": -0.95312783,
      "market_cap_rank": 113
    },
    {
      "id": 30494,
      "symbol": "EIGEN",
      "name": "EigenLayer",
      "current_price": 1.7369381254784342,
      "market_cap": 587438260.7431066,
      "total_volume": 232079115.55080497,
      "price_change_percentage_24h": 1.66753382,
      "market_cap_rank": 114
    },
    {
      "id": 1966,
      "symbol": "MANA",
      "name": "Decentraland",
      "current_price": 0.2950765073170986,
      "market_cap": 581220756.740778,
      "total_volume": 36390025.55404855,
      "price_change_percentage_24h": 1.61821082,
      "market_cap_rank": 115
    },
    {
      "id": 4558,
      "symbol": "FLOW",
      "name": "Flow",
      "current_price": 0.35991606264042925,
      "market_cap": 579413817.9116879,
      "total_volume": 15740045.49111689,
      "price_change_percentage_24h": 0.62395438,
      "market_cap_rank": 116
    },
    {
      "id": 36119,
      "symbol": "WAL",
      "name": "Walrus",
      "current_price": 0.39117983700653347,
      "market_cap": 565743839.270699,
      "total_volume": 13289565.36032973,
      "price_change_percentage_24h": 1.73895672,
      "market_cap_rank": 117
    },
    {
      "id": 5964,
      "symbol": "TWT",
      "name": "Trust Wallet Token",
      "current_price": 1.1993999689943369,
      "market_cap": 515574688.91461366,
      "total_volume": 96221185.33424272,
      "price_change_percentage_24h": 3.94658752,
      "market_cap_rank": 119
    },
    {
      "id": 38299,
      "symbol": "AVNT",
      "name": "Avantis",
      "current_price": 1.9481115208478714,
      "market_cap": 503013894.67097545,
      "total_volume": 1991044870.3076713,
      "price_change_percentage_24h": -5.44822364,
      "market_cap_rank": 120
    },
    {
      "id": 29587,
      "symbol": "W",
      "name": "Wormhole",
      "current_price": 0.10354934286515668,
      "market_cap": 494151577.0995655,
      "total_volume": 117561503.58255738,
      "price_change_percentage_24h": -4.05306325,
      "market_cap_rank": 121
    },
    {
      "id": 22691,
      "symbol": "STRK",
      "name": "Starknet",
      "current_price": 0.11948283618206534,
      "market_cap": 487147061.06244206,
      "total_volume": 33652403.21820709,
      "price_change_percentage_24h": 0.52785752,
      "market_cap_rank": 124
    },
    {
      "id": 33824,
      "symbol": "SYRUP",
      "name": "Maple Finance",
      "current_price": 0.4039833757503696,
      "market_cap": 483690880.6597164,
      "total_volume": 30461534.7335391,
      "price_change_percentage_24h": 1.11360035,
      "market_cap_rank": 125
    },
    {
      "id": 26997,
      "symbol": "ZRO",
      "name": "LayerZero",
      "current_price": 1.9070649773670734,
      "market_cap": 472279657.75594056,
      "total_volume": 82974213.4250385,
      "price_change_percentage_24h": 4.27179076,
      "market_cap_rank": 126
    },
    {
      "id": 28324,
      "symbol": "DYDX",
      "name": "dYdX",
      "current_price": 0.6036522192147061,
      "market_cap": 472490962.41222346,
      "total_volume": 26907801.26306956,
      "price_change_percentage_24h": -2.93656826,
      "market_cap_rank": 127
    },
    {
      "id": 23635,
      "symbol": "FORM",
      "name": "Four",
      "current_price": 1.1597928559657689,
      "market_cap": 442886914.4439344,
      "total_volume": 55200877.643818,
      "price_change_percentage_24h": -10.62113794,
      "market_cap_rank": 128
    },
    {
      "id": 27657,
      "symbol": "LINEA",
      "name": "Linea",
      "current_price": 0.028475290933487826,
      "market_cap": 440858664.304023,
      "total_volume": 471707087.3376211,
      "price_change_percentage_24h": -1.77397284,
      "market_cap_rank": 129
    },
    {
      "id": 9816,
      "symbol": "NFT",
      "name": "APENFT",
      "current_price": 4.373415277451745e-07,
      "market_cap": 437337154.32989705,
      "total_volume": 15910093.37676939,
      "price_change_percentage_24h": -0.27406018,
      "market_cap_rank": 131
    },
    {
      "id": 29743,
      "symbol": "BRETT",
      "name": "Brett (Based)",
      "current_price": 0.04292013336544334,
      "market_cap": 425348667.75647044,
      "total_volume": 39149108.118796,
      "price_change_percentage_24h": 0.58141469,
      "market_cap_rank": 132
    },
    {
      "id": 1376,
      "symbol": "NEO",
      "name": "Neo",
      "current_price": 6.005027390277544,
      "market_cap": 423587612.2331587,
      "total_volume": 23232184.94078851,
      "price_change_percentage_24h": 0.03279995,
      "market_cap_rank": 133
    },
    {
      "id": 30636,
      "symbol": "ZBCN",
      "name": "Zebec Network",
      "current_price": 0.004572132818669527,
      "market_cap": 420431563.1134049,
      "total_volume": 30935584.48223484,
      "price_change_percentage_24h": 23.59080658,
      "market_cap_rank": 134
    },
    {
      "id": 4157,
      "symbol": "RUNE",
      "name": "THORChain",
      "current_price": 1.1956778821786798,
      "market_cap": 420033811.9062756,
      "total_volume": 38971292.1794093,
      "price_change_percentage_24h": 1.72987195,
      "market_cap_rank": 135
    },
    {
      "id": 23254,
      "symbol": "CORE",
      "name": "Core",
      "current_price": 0.40985199061082667,
      "market_cap": 414943386.8856832,
      "total_volume": 26758075.85918335,
      "price_change_percentage_24h": -0.13186229,
      "market_cap_rank": 136
    },
    {
      "id": 33391,
      "symbol": "DEEP",
      "name": "DeepBook Protocol",
      "current_price": 0.11673035205216976,
      "market_cap": 411241030.2797941,
      "total_volume": 21141977.27610499,
      "price_change_percentage_24h": -0.44050531,
      "market_cap_rank": 137
    },
    {
      "id": 24091,
      "symbol": "ZK",
      "name": "ZKsync",
      "current_price": 0.05042086939721945,
      "market_cap": 406721009.4733392,
      "total_volume": 22307912.73942227,
      "price_change_percentage_24h": 1.93822118,
      "market_cap_rank": 138
    },
    {
      "id": 18876,
      "symbol": "APE",
      "name": "ApeCoin",
      "current_price": 0.5373381093473466,
      "market_cap": 404428342.0675161,
      "total_volume": 41534890.54787652,
      "price_change_percentage_24h": 0.36797825,
      "market_cap_rank": 139
    },
    {
      "id": 4066,
      "symbol": "CHZ",
      "name": "Chiliz",
      "current_price": 0.03964287931517321,
      "market_cap": 396478496.2838169,
      "total_volume": 35400012.32487717,
      "price_change_percentage_24h": 1.71166655,
      "market_cap_rank": 140
    },
    {
      "id": 5692,
      "symbol": "COMP",
      "name": "Compound",
      "current_price": 41.74937667136036,
      "market_cap": 395303147.942321,
      "total_volume": 30823074.62163128,
      "price_change_percentage_24h": 0.54467592,
      "market_cap_rank": 141
    },
    {
      "id": 5632,
      "symbol": "AR",
      "name": "Arweave",
      "current_price": 5.984786095998782,
      "market_cap": 392915965.68483275,
      "total_volume": 39524773.65806136,
      "price_change_percentage_24h": -0.56044418,
      "market_cap_rank": 142
    },
    {
      "id": 18679,
      "symbol": "XCN",
      "name": "Onyxcoin",
      "current_price": 0.010863726095874753,
      "market_cap": 380840679.1931359,
      "total_volume": 14968045.74616927,
      "price_change_percentage_24h": -2.24344299,
      "market_cap_rank": 143
    },
    {
      "id": 6892,
      "symbol": "EGLD",
      "name": "MultiversX",
      "current_price": 13.133942148355352,
      "market_cap": 376065945.31607896,
      "total_volume": 17958469.46329397,
      "price_change_percentage_24h": 0.84232769,
      "market_cap_rank": 144
    },
    {
      "id": 6783,
      "symbol": "AXS",
      "name": "Axie Infinity",
      "current_price": 2.226782064084456,
      "market_cap": 370726120.2051107,
      "total_volume": 36852485.72895424,
      "price_change_percentage_24h": 1.24089066,
      "market_cap_rank": 145
    },
    {
      "id": 36532,
      "symbol": "B",
      "name": "BUILDon",
      "current_price": 0.3684050304478496,
      "market_cap": 368405030.44784963,
      "total_volume": 13957585.81619705,
      "price_change_percentage_24h": -13.113428,
      "market_cap_rank": 146
    },
    {
      "id": 28298,
      "symbol": "BEAM",
      "name": "Beam",
      "current_price": 0.007386428406186654,
      "market_cap": 365377098.3270626,
      "total_volume": 15232125.77586561,
      "price_change_percentage_24h": 0.8448123,
      "market_cap_rank": 148
    },
    {
      "id": 3964,
      "symbol": "RSR",
      "name": "Reserve Rights",
      "current_price": 0.005961291800783424,
      "market_cap": 357611942.9281668,
      "total_volume": 40231875.43443608,
      "price_change_percentage_24h": -8.51077312,
      "market_cap_rank": 150
    },
    {
      "id": 9104,
      "symbol": "AIOZ",
      "name": "AIOZ Network",
      "current_price": 0.29019605537231696,
      "market_cap": 349710257.62527186,
      "total_volume": 10889302.61644266,
      "price_change_percentage_24h": -3.75735392,
      "market_cap_rank": 151
    },
    {
      "id": 4846,
      "symbol": "KAVA",
      "name": "Kava",
      "current_price": 0.32130852648308195,
      "market_cap": 347929923.355456,
      "total_volume": 10465648.16069021,
      "price_change_percentage_24h": -0.93410333,
      "market_cap_rank": 152
    },
    {
      "id": 9903,
      "symbol": "CVX",
      "name": "Convex Finance",
      "current_price": 3.4244420386000223,
      "market_cap": 331430544.0549506,
      "total_volume": 13034976.0491756,
      "price_change_percentage_24h": 1.77389031,
      "market_cap_rank": 156
    },
    {
      "id": 17799,
      "symbol": "AXL",
      "name": "Axelar",
      "current_price": 0.316814574734581,
      "market_cap": 329728866.3527956,
      "total_volume": 21499543.28617802,
      "price_change_percentage_24h": 9.01960424,
      "market_cap_rank": 157
    },
    {
      "id": 8104,
      "symbol": "1INCH",
      "name": "1inch",
      "current_price": 0.23406858578907033,
      "market_cap": 327193569.2740576,
      "total_volume": 17063059.9357348,
      "price_change_percentage_24h": 0.87503094,
      "market_cap_rank": 158
    },
    {
      "id": 5488,
      "symbol": "JST",
      "name": "JUST",
      "current_price": 0.03286539126334436,
      "market_cap": 325367373.50710917,
      "total_volume": 73953988.33222722,
      "price_change_percentage_24h": 2.03126124,
      "market_cap_rank": 159
    },
    {
      "id": 24647,
      "symbol": "BERA",
      "name": "Berachain",
      "current_price": 2.539589865689936,
      "market_cap": 320777933.88015443,
      "total_volume": 67860346.15950933,
      "price_change_percentage_24h": 2.74223318,
      "market_cap_rank": 160
    },
    {
      "id": 32452,
      "symbol": "MOVE",
      "name": "Movement",
      "current_price": 0.1160192266526844,
      "market_cap": 319052873.29488206,
      "total_volume": 33864772.378341,
      "price_change_percentage_24h": -1.05758627,
      "market_cap_rank": 161
    },
    {
      "id": 27750,
      "symbol": "TOSHI",
      "name": "Toshi",
      "current_price": 0.0007444784220084554,
      "market_cap": 313186322.9258273,
      "total_volume": 39196562.95326912,
      "price_change_percentage_24h": -0.70419173,
      "market_cap_rank": 162
    },
    {
      "id": 35364,
      "symbol": "PLUME",
      "name": "Plume",
      "current_price": 0.10126623970774311,
      "market_cap": 307299838.65160215,
      "total_volume": 37819835.37267169,
      "price_change_percentage_24h": -4.00145566,
      "market_cap_rank": 163
    },
    {
      "id": 7431,
      "symbol": "AKT",
      "name": "Akash Network",
      "current_price": 1.042176731013133,
      "market_cap": 290747519.8555879,
      "total_volume": 12017681.02401477,
      "price_change_percentage_24h": -0.026178,
      "market_cap_rank": 165
    },
    {
      "id": 3640,
      "symbol": "LPT",
      "name": "Livepeer",
      "current_price": 6.406193246656992,
      "market_cap": 286441842.619875,
      "total_volume": 19830692.87488752,
      "price_change_percentage_24h": 2.52367744,
      "market_cap_rank": 167
    },
    {
      "id": 5198,
      "symbol": "CTC",
      "name": "Creditcoin",
      "current_price": 0.5768588250038659,
      "market_cap": 280593392.79659814,
      "total_volume": 10393426.9534388,
      "price_change_percentage_24h": 1.35677409,
      "market_cap_rank": 168
    },
    {
      "id": 30712,
      "symbol": "MERL",
      "name": "Merlin Chain",
      "current_price": 0.2825583166428865,
      "market_cap": 276612938.7232909,
      "total_volume": 111315908.42061731,
      "price_change_percentage_24h": -9.79797171,
      "market_cap_rank": 169
    },
    {
      "id": 31278,
      "symbol": "DRIFT",
      "name": "Drift",
      "current_price": 0.7342144057196669,
      "market_cap": 270214282.3512461,
      "total_volume": 51927304.21632089,
      "price_change_percentage_24h": 0.32506781,
      "market_cap_rank": 172
    },
    {
      "id": 27659,
      "symbol": "MOG",
      "name": "Mog Coin",
      "current_price": 6.724586969289925e-07,
      "market_cap": 262640529.88806072,
      "total_volume": 26127969.13824023,
      "price_change_percentage_24h": -9.81171909,
      "market_cap_rank": 174
    },
    {
      "id": 131,
      "symbol": "DASH",
      "name": "Dash",
      "current_price": 21.10389400767639,
      "market_cap": 262193755.88155976,
      "total_volume": 28409592.33431363,
      "price_change_percentage_24h": 0.4929061,
      "market_cap_rank": 175
    },
    {
      "id": 34812,
      "symbol": "BIO",
      "name": "Bio Protocol",
      "current_price": 0.15149077805773828,
      "market_cap": 253260595.72986895,
      "total_volume": 79193419.96351811,
      "price_change_percentage_24h": 0.8468004,
      "market_cap_rank": 176
    },
    {
      "id": 35763,
      "symbol": "KAITO",
      "name": "KAITO",
      "current_price": 1.022421089932235,
      "market_cap": 246801090.9889113,
      "total_volume": 22055311.19001912,
      "price_change_percentage_24h": -0.2588411,
      "market_cap_rank": 179
    },
    {
      "id": 24911,
      "symbol": "TURBO",
      "name": "Turbo",
      "current_price": 0.0035768105855269543,
      "market_cap": 246799930.40135986,
      "total_volume": 26504712.22303044,
      "price_change_percentage_24h": 0.61779298,
      "market_cap_rank": 180
    },
    {
      "id": 5034,
      "symbol": "KSM",
      "name": "Kusama",
      "current_price": 14.385383544746546,
      "market_cap": 245755766.23489502,
      "total_volume": 10706490.07580638,
      "price_change_percentage_24h": 1.80100133,
      "market_cap_rank": 181
    },
    {
      "id": 30126,
      "symbol": "MEW",
      "name": "cat in a dogs world",
      "current_price": 0.002737296331535226,
      "market_cap": 243315229.46736473,
      "total_volume": 37128180.13753106,
      "price_change_percentage_24h": 0.20086098,
      "market_cap_rank": 183
    },
    {
      "id": 38408,
      "symbol": "BARD",
      "name": "Lombard",
      "current_price": 1.0695864464047413,
      "market_cap": 240656950.4410668,
      "total_volume": 272414262.8120129,
      "price_change_percentage_24h": 12.13736905,
      "market_cap_rank": 184
    },
    {
      "id": 7127,
      "symbol": "VELO",
      "name": "Velo",
      "current_price": 0.013686484215072984,
      "market_cap": 240387713.2034449,
      "total_volume": 22286548.98599923,
      "price_change_percentage_24h": 1.08371641,
      "market_cap_rank": 185
    },
    {
      "id": 31526,
      "symbol": "MOCA",
      "name": "Moca Network",
      "current_price": 0.06501495114634609,
      "market_cap": 235684816.37291646,
      "total_volume": 14683003.74678119,
      "price_change_percentage_24h": -1.37350401,
      "market_cap_rank": 186
    },
    {
      "id": 1684,
      "symbol": "QTUM",
      "name": "Qtum",
      "current_price": 2.193414622131252,
      "market_cap": 232108524.84209222,
      "total_volume": 45068337.26123992,
      "price_change_percentage_24h": 0.94003907,
      "market_cap_rank": 187
    },
    {
      "id": 2586,
      "symbol": "SNX",
      "name": "Synthetix",
      "current_price": 0.6703616585226599,
      "market_cap": 230246582.87355036,
      "total_volume": 25238804.19368001,
      "price_change_percentage_24h": 9.10204668,
      "market_cap_rank": 188
    },
    {
      "id": 28782,
      "symbol": "POPCAT",
      "name": "Popcat (SOL)",
      "current_price": 0.22969154406514417,
      "market_cap": 225091553.91321057,
      "total_volume": 35631842.96898576,
      "price_change_percentage_24h": 0.73425277,
      "market_cap_rank": 191
    },
    {
      "id": 1697,
      "symbol": "BAT",
      "name": "Basic Attention Token",
      "current_price": 0.1453075497168955,
      "market_cap": 217335929.1570053,
      "total_volume": 10214253.25744653,
      "price_change_percentage_24h": 0.92026354,
      "market_cap_rank": 196
    },
    {
      "id": 33788,
      "symbol": "PNUT",
      "name": "Peanut the Squirrel",
      "current_price": 0.21499661582112517,
      "market_cap": 214964760.6968535,
      "total_volume": 45845535.28145538,
      "price_change_percentage_24h": 2.34812625,
      "market_cap_rank": 198
    },
    {
      "id": 2469,
      "symbol": "ZIL",
      "name": "Zilliqa",
      "current_price": 0.010916256685529674,
      "market_cap": 213259002.38874704,
      "total_volume": 14448470.92071456,
      "price_change_percentage_24h": 0.63292681,
      "market_cap_rank": 199
    },
    {
      "id": 4948,
      "symbol": "CKB",
      "name": "Nervos Network",
      "current_price": 0.004479084764748281,
      "market_cap": 211932530.12655994,
      "total_volume": 14731282.30861648,
      "price_change_percentage_24h": -0.05291343,
      "market_cap_rank": 200
    },
    {
      "id": 29082,
      "symbol": "SAROS",
      "name": "Saros",
      "current_price": 0.40296386135082096,
      "market_cap": 1057780136.045905,
      "total_volume": 11179203.65341016,
      "price_change_percentage_24h": 0.31422964,
      "market_cap_rank": 204
    },
    {
      "id": 16334,
      "symbol": "APX",
      "name": "APX",
      "current_price": 1.6704810275449928,
      "market_cap": 889547635.2912495,
      "total_volume": 48490755.83541364,
      "price_change_percentage_24h": 10.60243477,
      "market_cap_rank": 205
    },
    {
      "id": 36066,
      "symbol": "KTA",
      "name": "Keeta",
      "current_price": 1.0308557561477951,
      "market_cap": 437981382.63615906,
      "total_volume": 22392211.53214695,
      "price_change_percentage_24h": -9.4276777,
      "market_cap_rank": 212
    },
    {
      "id": 8646,
      "symbol": "MINA",
      "name": "Mina",
      "current_price": 0.16686066838924402,
      "market_cap": 209156069.40625122,
      "total_volume": 10099088.30878912,
      "price_change_percentage_24h": -0.25769694,
      "market_cap_rank": 224
    },
    {
      "id": 30986,
      "symbol": "KMNO",
      "name": "Kamino Finance",
      "current_price": 0.07308098559429586,
      "market_cap": 207730205.92747918,
      "total_volume": 28472438.90264592,
      "price_change_percentage_24h": -5.07090261,
      "market_cap_rank": 225
    },
    {
      "id": 1896,
      "symbol": "ZRX",
      "name": "0x Protocol",
      "current_price": 0.24068664931936434,
      "market_cap": 204197726.01782703,
      "total_volume": 25291055.40099175,
      "price_change_percentage_24h": 3.00348537,
      "market_cap_rank": 227
    },
    {
      "id": 10407,
      "symbol": "BabyDoge",
      "name": "Baby Doge Coin",
      "current_price": 1.201775737614274e-09,
      "market_cap": 203058022.16039082,
      "total_volume": 13249388.87683471,
      "price_change_percentage_24h": -0.2303321,
      "market_cap_rank": 230
    },
    {
      "id": 35931,
      "symbol": "ZORA",
      "name": "ZORA",
      "current_price": 0.0605563433560896,
      "market_cap": 200419839.60466674,
      "total_volume": 65504285.04711355,
      "price_change_percentage_24h": 3.72944903,
      "market_cap_rank": 232
    },
    {
      "id": 6758,
      "symbol": "SUSHI",
      "name": "SushiSwap",
      "current_price": 0.6804270245193443,
      "market_cap": 194191426.37816557,
      "total_volume": 31433811.19470722,
      "price_change_percentage_24h": 1.46593515,
      "market_cap_rank": 237
    },
    {
      "id": 35818,
      "symbol": "SOSO",
      "name": "SoSoValue",
      "current_price": 0.6980041083133413,
      "market_cap": 191788198.8751899,
      "total_volume": 10940256.91929667,
      "price_change_percentage_24h": -0.28020175,
      "market_cap_rank": 238
    },
    {
      "id": 23121,
      "symbol": "BLUR",
      "name": "Blur",
      "current_price": 0.07567661009318688,
      "market_cap": 191093246.38715613,
      "total_volume": 17587383.09238254,
      "price_change_percentage_24h": -0.2549633,
      "market_cap_rank": 239
    },
    {
      "id": 32956,
      "symbol": "GRASS",
      "name": "Grass",
      "current_price": 0.7602195175667131,
      "market_cap": 185421410.61208525,
      "total_volume": 44732819.24875087,
      "price_change_percentage_24h": 1.51659547,
      "market_cap_rank": 242
    },
    {
      "id": 6536,
      "symbol": "OM",
      "name": "MANTRA",
      "current_price": 0.17196236045629268,
      "market_cap": 184355096.91669503,
      "total_volume": 72289355.56634994,
      "price_change_percentage_24h": -2.29386614,
      "market_cap_rank": 244
    },
    {
      "id": 21846,
      "symbol": "ID",
      "name": "SPACE ID",
      "current_price": 0.1528189247202935,
      "market_cap": 181209383.87527767,
      "total_volume": 18698876.6417136,
      "price_change_percentage_24h": -2.5095386,
      "market_cap_rank": 245
    },
    {
      "id": 25028,
      "symbol": "ORDI",
      "name": "ORDI",
      "current_price": 8.528355181735323,
      "market_cap": 179095458.81644177,
      "total_volume": 49316906.93385255,
      "price_change_percentage_24h": -1.47082969,
      "market_cap_rank": 247
    },
    {
      "id": 21259,
      "symbol": "ZETA",
      "name": "ZetaChain",
      "current_price": 0.17398788729287332,
      "market_cap": 178069353.090956,
      "total_volume": 12703994.07513299,
      "price_change_percentage_24h": 0.19814316,
      "market_cap_rank": 248
    },
    {
      "id": 36671,
      "symbol": "SAHARA",
      "name": "Sahara AI",
      "current_price": 0.07980692851467151,
      "market_cap": 176256926.93994245,
      "total_volume": 28675280.99134054,
      "price_change_percentage_24h": -1.45439058,
      "market_cap_rank": 249
    },
    {
      "id": 6958,
      "symbol": "ACH",
      "name": "Alchemy Pay",
      "current_price": 0.018286760992210153,
      "market_cap": 174178406.02221206,
      "total_volume": 23679745.80959631,
      "price_change_percentage_24h": 1.03112227,
      "market_cap_rank": 252
    },
    {
      "id": 5864,
      "symbol": "YFI",
      "name": "yearn.finance",
      "current_price": 5134.417793338633,
      "market_cap": 174080884.0694539,
      "total_volume": 14047307.99640148,
      "price_change_percentage_24h": 1.28159159,
      "market_cap_rank": 253
    },
    {
      "id": 38359,
      "symbol": "STBL",
      "name": "STBL",
      "current_price": 0.3421923395516052,
      "market_cap": 171096169.7758026,
      "total_volume": 174609656.8051714,
      "price_change_percentage_24h": -8.04484525,
      "market_cap_rank": 255
    },
    {
      "id": 28850,
      "symbol": "NOT",
      "name": "Notcoin",
      "current_price": 0.0016772417463464364,
      "market_cap": 166774266.7745049,
      "total_volume": 25289562.70715646,
      "price_change_percentage_24h": 2.33559731,
      "market_cap_rank": 257
    },
    {
      "id": 4006,
      "symbol": "AWE",
      "name": "AWE",
      "current_price": 0.08551677644873905,
      "market_cap": 166109521.11312214,
      "total_volume": 52002164.15090632,
      "price_change_percentage_24h": 5.82573976,
      "market_cap_rank": 258
    },
    {
      "id": 30746,
      "symbol": "BB",
      "name": "BounceBit",
      "current_price": 0.20512723926495552,
      "market_cap": 162818201.1481923,
      "total_volume": 123114770.78554496,
      "price_change_percentage_24h": -2.42727346,
      "market_cap_rank": 259
    },
    {
      "id": 37637,
      "symbol": "SOMI",
      "name": "Somnia",
      "current_price": 1.0097783628276515,
      "market_cap": 161766493.72498977,
      "total_volume": 197969682.87152642,
      "price_change_percentage_24h": 3.83688912,
      "market_cap_rank": 261
    },
    {
      "id": 36828,
      "symbol": "USELESS",
      "name": "Useless Coin",
      "current_price": 0.15907270498398146,
      "market_cap": 158928123.29471442,
      "total_volume": 50738902.63770883,
      "price_change_percentage_24h": -0.05677471,
      "market_cap_rank": 262
    },
    {
      "id": 37456,
      "symbol": "OPEN",
      "name": "OpenLedger",
      "current_price": 0.736459185901671,
      "market_cap": 158706954.5618101,
      "total_volume": 524582496.6030578,
      "price_change_percentage_24h": -12.24873064,
      "market_cap_rank": 263
    },
    {
      "id": 5567,
      "symbol": "CELO",
      "name": "Celo",
      "current_price": 0.26882175625892235,
      "market_cap": 156295725.58722612,
      "total_volume": 12415408.04064149,
      "price_change_percentage_24h": -0.97056523,
      "market_cap_rank": 266
    },
    {
      "id": 37593,
      "symbol": "PROVE",
      "name": "Succinct",
      "current_price": 0.7820893359239695,
      "market_cap": 152507420.50517404,
      "total_volume": 38864130.87604845,
      "price_change_percentage_24h": -5.77749892,
      "market_cap_rank": 270
    },
    {
      "id": 11857,
      "symbol": "GMX",
      "name": "GMX",
      "current_price": 14.64097970990107,
      "market_cap": 150820171.41591215,
      "total_volume": 14606443.73148962,
      "price_change_percentage_24h": 3.3990739,
      "market_cap_rank": 272
    },
    {
      "id": 14588,
      "symbol": "PEAQ",
      "name": "peaq",
      "current_price": 0.11562108701764809,
      "market_cap": 149675980.11133155,
      "total_volume": 16984990.44449441,
      "price_change_percentage_24h": 0.89238772,
      "market_cap_rank": 273
    },
    {
      "id": 21296,
      "symbol": "ETHW",
      "name": "EthereumPoW",
      "current_price": 1.3870953732214875,
      "market_cap": 149555234.72752985,
      "total_volume": 10749141.75720084,
      "price_change_percentage_24h": -1.89400059,
      "market_cap_rank": 274
    },
    {
      "id": 33093,
      "symbol": "MOODENG",
      "name": "Moo Deng (moodengsol.com)",
      "current_price": 0.14941473843685957,
      "market_cap": 147916376.2375349,
      "total_volume": 49453132.74808029,
      "price_change_percentage_24h": -0.52269936,
      "market_cap_rank": 276
    },
    {
      "id": 21707,
      "symbol": "RED",
      "name": "RedStone",
      "current_price": 0.5164060590773218,
      "market_cap": 146215881.34581152,
      "total_volume": 15767769.51812731,
      "price_change_percentage_24h": -3.31359481,
      "market_cap_rank": 277
    },
    {
      "id": 5691,
      "symbol": "SKL",
      "name": "SKALE",
      "current_price": 0.024505361021141283,
      "market_cap": 146066720.35643402,
      "total_volume": 14848641.21214351,
      "price_change_percentage_24h": -0.59761246,
      "market_cap_rank": 279
    },
    {
      "id": 6748,
      "symbol": "CFG",
      "name": "Centrifuge",
      "current_price": 0.25745932768684937,
      "market_cap": 145491068.06164432,
      "total_volume": 12859734.18567487,
      "price_change_percentage_24h": 10.59960896,
      "market_cap_rank": 280
    },
    {
      "id": 32198,
      "symbol": "BABY",
      "name": "Babylon",
      "current_price": 0.05394541185705841,
      "market_cap": 142939177.0550808,
      "total_volume": 32034890.4720953,
      "price_change_percentage_24h": -5.01920856,
      "market_cap_rank": 284
    },
    {
      "id": 30315,
      "symbol": "OMNI",
      "name": "Omni Network",
      "current_price": 4.145396258184196,
      "market_cap": 142928372.89268407,
      "total_volume": 128368061.26810794,
      "price_change_percentage_24h": -2.268315,
      "market_cap_rank": 285
    },
    {
      "id": 23951,
      "symbol": "STIK",
      "name": "Staika",
      "current_price": 1.0947701843568751,
      "market_cap": 141105241.7114124,
      "total_volume": 39340433.01064605,
      "price_change_percentage_24h": -1.82574992,
      "market_cap_rank": 287
    },
    {
      "id": 3945,
      "symbol": "ONE",
      "name": "Harmony",
      "current_price": 0.009430524519424072,
      "market_cap": 138805654.1388878,
      "total_volume": 10553583.65736717,
      "price_change_percentage_24h": 2.35354946,
      "market_cap_rank": 288
    },
    {
      "id": 1732,
      "symbol": "NMR",
      "name": "Numeraire",
      "current_price": 17.76621767505285,
      "market_cap": 135068881.12050745,
      "total_volume": 139854307.1686675,
      "price_change_percentage_24h": 19.39157517,
      "market_cap_rank": 292
    },
    {
      "id": 2765,
      "symbol": "XYO",
      "name": "XYO",
      "current_price": 0.009730672137881072,
      "market_cap": 132874130.43681768,
      "total_volume": 11943166.7925627,
      "price_change_percentage_24h": -0.11396482,
      "market_cap_rank": 293
    },
    {
      "id": 28301,
      "symbol": "MEME",
      "name": "Memecoin",
      "current_price": 0.0023556777185798315,
      "market_cap": 130269523.81083323,
      "total_volume": 53391393.86894966,
      "price_change_percentage_24h": 0.95839197,
      "market_cap_rank": 296
    },
    {
      "id": 38371,
      "symbol": "ZKC",
      "name": "Boundless",
      "current_price": 0.6353053115708629,
      "market_cap": 127656378.96821192,
      "total_volume": 186580473.61306417,
      "price_change_percentage_24h": -11.19162563,
      "market_cap_rank": 300
    },
    {
      "id": 36044,
      "symbol": "NXPC",
      "name": "NEXPACE",
      "current_price": 0.6164933669835788,
      "market_cap": 127320565.15411058,
      "total_volume": 17690859.89031059,
      "price_change_percentage_24h": -1.76275044,
      "market_cap_rank": 302
    },
    {
      "id": 35429,
      "symbol": "LAYER",
      "name": "Solayer",
      "current_price": 0.44570813098042594,
      "market_cap": 126411918.27543151,
      "total_volume": 28872145.30043561,
      "price_change_percentage_24h": -4.58960934,
      "market_cap_rank": 304
    },
    {
      "id": 7501,
      "symbol": "WOO",
      "name": "WOO",
      "current_price": 0.06497450861027329,
      "market_cap": 123781221.48365568,
      "total_volume": 11539426.66380614,
      "price_change_percentage_24h": -2.13521004,
      "market_cap_rank": 307
    },
    {
      "id": 27565,
      "symbol": "ARKM",
      "name": "Arkham",
      "current_price": 0.5495930857803878,
      "market_cap": 123713403.6091653,
      "total_volume": 67050331.17245662,
      "price_change_percentage_24h": 1.98856287,
      "market_cap_rank": 308
    },
    {
      "id": 38159,
      "symbol": "HEMI",
      "name": "Hemi",
      "current_price": 0.12603584324009678,
      "market_cap": 123200036.76719461,
      "total_volume": 740589764.2401781,
      "price_change_percentage_24h": 57.49268004,
      "market_cap_rank": 309
    },
    {
      "id": 29073,
      "symbol": "ALT",
      "name": "Altlayer",
      "current_price": 0.029063532891026436,
      "market_cap": 123134768.5438741,
      "total_volume": 24184875.52650987,
      "price_change_percentage_24h": -0.43061313,
      "market_cap_rank": 310
    },
    {
      "id": 8536,
      "symbol": "MASK",
      "name": "Mask Network",
      "current_price": 1.2220784152853064,
      "market_cap": 122207841.52853064,
      "total_volume": 20128671.55800731,
      "price_change_percentage_24h": 1.7078545,
      "market_cap_rank": 313
    },
    {
      "id": 18069,
      "symbol": "GMT",
      "name": "GMT",
      "current_price": 0.03917936822777742,
      "market_cap": 121902692.38071159,
      "total_volume": 20345713.51310135,
      "price_change_percentage_24h": 1.23547423,
      "market_cap_rank": 314
    },
    {
      "id": 34619,
      "symbol": "VANA",
      "name": "Vana",
      "current_price": 4.01888683328315,
      "market_cap": 120904191.49249029,
      "total_volume": 41773772.49409469,
      "price_change_percentage_24h": -7.59567532,
      "market_cap_rank": 315
    },
    {
      "id": 32521,
      "symbol": "NEIRO",
      "name": "Neiro",
      "current_price": 0.0002866111964372237,
      "market_cap": 120572920.34596798,
      "total_volume": 44449981.9583583,
      "price_change_percentage_24h": -4.26510462,
      "market_cap_rank": 316
    },
    {
      "id": 1274,
      "symbol": "WAVES",
      "name": "Waves",
      "current_price": 1.0118045569331378,
      "market_cap": 120291717.63520662,
      "total_volume": 16947821.46578936,
      "price_change_percentage_24h": -0.75006421,
      "market_cap_rank": 317
    },
    {
      "id": 11165,
      "symbol": "ORCA",
      "name": "Orca",
      "current_price": 2.0000533943751293,
      "market_cap": 119917664.07910642,
      "total_volume": 10830933.13880716,
      "price_change_percentage_24h": 0.57259407,
      "market_cap_rank": 319
    },
    {
      "id": 29870,
      "symbol": "BOME",
      "name": "BOOK OF MEME",
      "current_price": 0.0017309192520427058,
      "market_cap": 119288141.3121683,
      "total_volume": 31778559.56135593,
      "price_change_percentage_24h": -0.469418,
      "market_cap_rank": 320
    },
    {
      "id": 2130,
      "symbol": "ENJ",
      "name": "Enjin Coin",
      "current_price": 0.06313025469994352,
      "market_cap": 118954214.83915076,
      "total_volume": 10603818.31917978,
      "price_change_percentage_24h": 1.19995018,
      "market_cap_rank": 323
    },
    {
      "id": 1698,
      "symbol": "ZEN",
      "name": "Horizen",
      "current_price": 6.84984440672888,
      "market_cap": 118766203.5202835,
      "total_volume": 10610807.74536584,
      "price_change_percentage_24h": 2.94320905,
      "market_cap_rank": 324
    },
    {
      "id": 32197,
      "symbol": "ME",
      "name": "Magic Eden",
      "current_price": 0.7077365284544286,
      "market_cap": 118285897.82660031,
      "total_volume": 236015901.804882,
      "price_change_percentage_24h": -12.54382021,
      "market_cap_rank": 325
    },
    {
      "id": 1934,
      "symbol": "LRC",
      "name": "Loopring",
      "current_price": 0.08383561253718394,
      "market_cap": 114612112.3261699,
      "total_volume": 11297145.78471451,
      "price_change_percentage_24h": -0.47510084,
      "market_cap_rank": 330
    },
    {
      "id": 29835,
      "symbol": "IO",
      "name": "io.net",
      "current_price": 0.5439081544378022,
      "market_cap": 111180007.1189488,
      "total_volume": 23381334.71718022,
      "price_change_percentage_24h": -0.12096834,
      "market_cap_rank": 336
    },
    {
      "id": 4679,
      "symbol": "BAND",
      "name": "Band",
      "current_price": 0.6660882028731516,
      "market_cap": 110607710.64538372,
      "total_volume": 10149858.84861921,
      "price_change_percentage_24h": 3.47028469,
      "market_cap_rank": 338
    },
    {
      "id": 36922,
      "symbol": "H",
      "name": "Humanity Protocol",
      "current_price": 0.05345895778081262,
      "market_cap": 110215124.92387865,
      "total_volume": 35338571.3613777,
      "price_change_percentage_24h": -9.41387991,
      "market_cap_rank": 340
    },
    {
      "id": 12999,
      "symbol": "SSV",
      "name": "ssv.network",
      "current_price": 7.842255622487692,
      "market_cap": 109875978.189276,
      "total_volume": 16519553.56592725,
      "price_change_percentage_24h": 0.32538506,
      "market_cap_rank": 341
    },
    {
      "id": 18934,
      "symbol": "STG",
      "name": "Stargate Finance",
      "current_price": 0.1647556799290142,
      "market_cap": 108895492.5291191,
      "total_volume": 16596630.32978502,
      "price_change_percentage_24h": 4.11146189,
      "market_cap_rank": 345
    },
    {
      "id": 5617,
      "symbol": "UMA",
      "name": "UMA",
      "current_price": 1.2041446858500113,
      "market_cap": 108518258.18196452,
      "total_volume": 10744308.92507545,
      "price_change_percentage_24h": 1.88661392,
      "market_cap_rank": 346
    },
    {
      "id": 32193,
      "symbol": "ALEO",
      "name": "Aleo",
      "current_price": 0.2080946152048879,
      "market_cap": 107667640.83034995,
      "total_volume": 168678667.4949958,
      "price_change_percentage_24h": -0.84673149,
      "market_cap_rank": 347
    },
    {
      "id": 35600,
      "symbol": "SIGN",
      "name": "Sign",
      "current_price": 0.07866495463620544,
      "market_cap": 106197688.75887735,
      "total_volume": 55229769.78742508,
      "price_change_percentage_24h": -7.65270744,
      "market_cap_rank": 353
    },
    {
      "id": 34026,
      "symbol": "AI16Z",
      "name": "ai16z",
      "current_price": 0.09305524010874193,
      "market_cap": 102360352.40140219,
      "total_volume": 260270432.92110255,
      "price_change_percentage_24h": -1.66593739,
      "market_cap_rank": 360
    },
    {
      "id": 37372,
      "symbol": "PTB",
      "name": "Portal To Bitcoin",
      "current_price": 0.05996518627208775,
      "market_cap": 101083997.12394965,
      "total_volume": 400813555.30336344,
      "price_change_percentage_24h": -0.72320534,
      "market_cap_rank": 362
    }
  ]
}